mlstars/__init__.py
mlstars/utils.py
mlstars/adapters/__init__.py
mlstars/adapters/keras.py
mlstars/adapters/pandas.py
mlstars/adapters/sklearn.py
mlstars/adapters/statsmodels.py
mlstars/custom/__init__.py
mlstars/custom/timeseries_anomalies.py
mlstars/custom/timeseries_preprocessing.py
mlstars/primitives/keras.Sequential.DoubleLSTMTimeSeriesClassifier.json
mlstars/primitives/keras.Sequential.LSTMTimeSeriesClassifier.json
mlstars/primitives/keras.Sequential.LSTMTimeSeriesRegressor.json
mlstars/primitives/mlstars.custom.timeseries_anomalies.find_anomalies.json
mlstars/primitives/mlstars.custom.timeseries_anomalies.regression_errors.json
mlstars/primitives/mlstars.custom.timeseries_preprocessing.cutoff_window_sequences.json
mlstars/primitives/mlstars.custom.timeseries_preprocessing.intervals_to_mask.json
mlstars/primitives/mlstars.custom.timeseries_preprocessing.rolling_window_sequences.json
mlstars/primitives/mlstars.custom.timeseries_preprocessing.time_segments_aggregate.json
mlstars/primitives/mlstars.custom.timeseries_preprocessing.time_segments_average.json
mlstars/primitives/numpy.argmax.json
mlstars/primitives/numpy.ravel.json
mlstars/primitives/numpy.reshape.json
mlstars/primitives/pandas.DataFrame.append.json
mlstars/primitives/pandas.DataFrame.drop.json
mlstars/primitives/pandas.DataFrame.drop_duplicates.json
mlstars/primitives/pandas.DataFrame.dropna.json
mlstars/primitives/pandas.DataFrame.fillna.json
mlstars/primitives/pandas.DataFrame.filter.json
mlstars/primitives/pandas.DataFrame.get.json
mlstars/primitives/pandas.DataFrame.join.json
mlstars/primitives/pandas.DataFrame.json
mlstars/primitives/pandas.DataFrame.pop.json
mlstars/primitives/pandas.DataFrame.resample.json
mlstars/primitives/pandas.DataFrame.select_dtypes.json
mlstars/primitives/pandas.DataFrame.set.json
mlstars/primitives/pandas.DataFrame.set_index.json
mlstars/primitives/pandas.DataFrame.to_numpy.json
mlstars/primitives/pandas.DataFrame.unstack.json
ml_stars-0.2.3.dist-info/AUTHORS.rst
ml_stars-0.2.3.dist-info/LICENSE
ml_stars-0.2.3.dist-info/METADATA
ml_stars-0.2.3.dist-info/WHEEL
ml_stars-0.2.3.dist-info/entry_points.txt
ml_stars-0.2.3.dist-info/top_level.txt
ml_stars-0.2.3.dist-info/RECORD
