Metadata-Version: 2.1
Name: ml-stars
Version: 0.2.3
Summary: Primitives and Pipelines for Time Series Data.
Home-page: https://github.com/sintel-dev/ml-stars
Author: MIT Data To AI Lab
Author-email: dailabmit@gmail.com
License: MIT license
Keywords: mlstars
Classifier: Development Status :: 2 - Pre-Alpha
Classifier: Intended Audience :: Developers
Classifier: License :: OSI Approved :: MIT License
Classifier: Natural Language :: English
Classifier: Programming Language :: Python :: 3
Classifier: Programming Language :: Python :: 3.8
Classifier: Programming Language :: Python :: 3.9
Classifier: Programming Language :: Python :: 3.10
Classifier: Programming Language :: Python :: 3.11
Classifier: Programming Language :: Python :: 3.12
Requires-Python: >=3.8,<3.13
License-File: LICENSE
License-File: AUTHORS.rst
Requires-Dist: Keras<4,>=2.4
Requires-Dist: mlblocks>=0.6.2
Requires-Dist: numpy<2,>=1.17.4
Requires-Dist: pandas<3,>=1
Requires-Dist: scikit-learn<2,>=0.22
Requires-Dist: scipy<2,>=1.4.1
Requires-Dist: statsmodels<0.15,>=0.12.0
Requires-Dist: tensorflow<3,>=2.2
Requires-Dist: xgboost<2,>=0.72.1
Requires-Dist: protobuf<4
Provides-Extra: dev
Requires-Dist: bumpversion<0.6,>=0.5.3; extra == "dev"
Requires-Dist: pip>=9.0.1; extra == "dev"
Requires-Dist: watchdog<7,>=0.8.3; extra == "dev"
Requires-Dist: docutils<0.18,>=0.12; extra == "dev"
Requires-Dist: m2r2<0.3,>=0.2.5; extra == "dev"
Requires-Dist: nbsphinx<0.7,>=0.5.0; extra == "dev"
Requires-Dist: Sphinx<3.3,>=3; extra == "dev"
Requires-Dist: pydata-sphinx-theme<0.5; extra == "dev"
Requires-Dist: markupsafe<2.1.0; extra == "dev"
Requires-Dist: ipython<9,>=6.5; extra == "dev"
Requires-Dist: Jinja2<3,>=2; extra == "dev"
Requires-Dist: alabaster<=0.7.12; extra == "dev"
Requires-Dist: sphinxcontrib-applehelp<1.0.8; extra == "dev"
Requires-Dist: sphinxcontrib-devhelp<1.0.6; extra == "dev"
Requires-Dist: sphinxcontrib-htmlhelp<2.0.5; extra == "dev"
Requires-Dist: sphinxcontrib-serializinghtml<1.1.10; extra == "dev"
Requires-Dist: sphinxcontrib-qthelp<1.0.7; extra == "dev"
Requires-Dist: flake8<4,>=3.7.7; extra == "dev"
Requires-Dist: isort<5,>=4.3.4; extra == "dev"
Requires-Dist: autoflake>=1.2; extra == "dev"
Requires-Dist: autopep8>=1.4.3; extra == "dev"
Requires-Dist: importlib-metadata<5; extra == "dev"
Requires-Dist: twine>=1.10.0; extra == "dev"
Requires-Dist: wheel>=0.30.0; extra == "dev"
Requires-Dist: coverage>=4.5.1; extra == "dev"
Requires-Dist: tox>=2.9.1; extra == "dev"
Requires-Dist: invoke; extra == "dev"
Requires-Dist: pytest>=3.4.2; extra == "dev"
Requires-Dist: pytest-cov>=2.6.0; extra == "dev"
Requires-Dist: rundoc<0.5,>=0.4.3; extra == "dev"
Provides-Extra: test
Requires-Dist: pytest>=3.4.2; extra == "test"
Requires-Dist: pytest-cov>=2.6.0; extra == "test"
Requires-Dist: rundoc<0.5,>=0.4.3; extra == "test"
